{
  "info": {
    "name": "NixTrack API",
    "description": "API collection for NixTrack tracking system",
    "schema": "https://schema.getpostman.com/json/collection/v2.1.0/collection.json"
  },
  "variable": [
    {
      "key": "baseUrl",
      "value": "http://localhost:3000/api",
      "type": "string"
    },
    {
      "key": "token",
      "value": "",
      "type": "string"
    }
  ],
  "item": [
    {
      "name": "Health",
      "item": [
        {
          "name": "Health Check",
          "request": {
            "method": "GET",
            "header": [],
            "url": {
              "raw": "{{baseUrl}}/health",
              "host": ["{{baseUrl}}"],
              "path": ["health"]
            },
            "description": "Check if the API is running"
          },
          "response": []
        }
      ]
    },
    {
      "name": "Auth",
      "item": [
        {
          "name": "Register",
          "event": [
            {
              "listen": "test",
              "script": {
                "exec": [
                  "if (pm.response.code === 201) {",
                  "    var jsonData = pm.response.json();",
                  "    pm.collectionVariables.set('token', jsonData.token);",
                  "}"
                ],
                "type": "text/javascript"
              }
            }
          ],
          "request": {
            "method": "POST",
            "header": [
              {
                "key": "Content-Type",
                "value": "application/json"
              }
            ],
            "body": {
              "mode": "raw",
              "raw": "{\n    \"name\": \"Admin User\",\n    \"email\": \"admin@nixtrack.com\",\n    \"password\": \"password123\",\n    \"document_id\": \"123456789\",\n    \"phone\": \"+57 300 123 4567\",\n    \"position\": \"Administrador\"\n}"
            },
            "url": {
              "raw": "{{baseUrl}}/auth/register",
              "host": ["{{baseUrl}}"],
              "path": ["auth", "register"]
            },
            "description": "Register a new user"
          },
          "response": []
        },
        {
          "name": "Login",
          "event": [
            {
              "listen": "test",
              "script": {
                "exec": [
                  "if (pm.response.code === 200) {",
                  "    var jsonData = pm.response.json();",
                  "    pm.collectionVariables.set('token', jsonData.token);",
                  "}"
                ],
                "type": "text/javascript"
              }
            }
          ],
          "request": {
            "method": "POST",
            "header": [
              {
                "key": "Content-Type",
                "value": "application/json"
              }
            ],
            "body": {
              "mode": "raw",
              "raw": "{\n    \"email\": \"admin@nixtrack.com\",\n    \"password\": \"password123\"\n}"
            },
            "url": {
              "raw": "{{baseUrl}}/auth/login",
              "host": ["{{baseUrl}}"],
              "path": ["auth", "login"]
            },
            "description": "Login and get JWT token"
          },
          "response": []
        },
        {
          "name": "Get Profile",
          "request": {
            "method": "GET",
            "header": [
              {
                "key": "Authorization",
                "value": "Bearer {{token}}"
              }
            ],
            "url": {
              "raw": "{{baseUrl}}/auth/profile",
              "host": ["{{baseUrl}}"],
              "path": ["auth", "profile"]
            },
            "description": "Get current user profile"
          },
          "response": []
        }
      ]
    },
    {
      "name": "Users",
      "item": [
        {
          "name": "List Users",
          "request": {
            "method": "GET",
            "header": [
              {
                "key": "Authorization",
                "value": "Bearer {{token}}"
              }
            ],
            "url": {
              "raw": "{{baseUrl}}/users",
              "host": ["{{baseUrl}}"],
              "path": ["users"]
            },
            "description": "Get all users (filtered by client_id for non-admins)"
          },
          "response": []
        },
        {
          "name": "Get User by ID",
          "request": {
            "method": "GET",
            "header": [
              {
                "key": "Authorization",
                "value": "Bearer {{token}}"
              }
            ],
            "url": {
              "raw": "{{baseUrl}}/users/1",
              "host": ["{{baseUrl}}"],
              "path": ["users", "1"]
            },
            "description": "Get a specific user by ID"
          },
          "response": []
        },
        {
          "name": "Update User",
          "request": {
            "method": "PUT",
            "header": [
              {
                "key": "Content-Type",
                "value": "application/json"
              },
              {
                "key": "Authorization",
                "value": "Bearer {{token}}"
              }
            ],
            "body": {
              "mode": "raw",
              "raw": "{\n    \"name\": \"Updated Name\",\n    \"phone\": \"+57 300 999 8888\",\n    \"position\": \"Supervisor\"\n}"
            },
            "url": {
              "raw": "{{baseUrl}}/users/1",
              "host": ["{{baseUrl}}"],
              "path": ["users", "1"]
            },
            "description": "Update user information"
          },
          "response": []
        },
        {
          "name": "Update User Password",
          "request": {
            "method": "PUT",
            "header": [
              {
                "key": "Content-Type",
                "value": "application/json"
              },
              {
                "key": "Authorization",
                "value": "Bearer {{token}}"
              }
            ],
            "body": {
              "mode": "raw",
              "raw": "{\n    \"password\": \"newpassword123\"\n}"
            },
            "url": {
              "raw": "{{baseUrl}}/users/1",
              "host": ["{{baseUrl}}"],
              "path": ["users", "1"]
            },
            "description": "Update user password"
          },
          "response": []
        },
        {
          "name": "Delete User (Soft)",
          "request": {
            "method": "DELETE",
            "header": [
              {
                "key": "Authorization",
                "value": "Bearer {{token}}"
              }
            ],
            "url": {
              "raw": "{{baseUrl}}/users/2",
              "host": ["{{baseUrl}}"],
              "path": ["users", "2"]
            },
            "description": "Soft delete (deactivate) a user"
          },
          "response": []
        },
        {
          "name": "Activate User",
          "request": {
            "method": "PATCH",
            "header": [
              {
                "key": "Authorization",
                "value": "Bearer {{token}}"
              }
            ],
            "url": {
              "raw": "{{baseUrl}}/users/2/activate",
              "host": ["{{baseUrl}}"],
              "path": ["users", "2", "activate"]
            },
            "description": "Reactivate a deactivated user (admin only)"
          },
          "response": []
        }
      ]
    },
    {
      "name": "Roles",
      "item": [
        {
          "name": "List Roles",
          "request": {
            "method": "GET",
            "header": [
              {
                "key": "Authorization",
                "value": "Bearer {{token}}"
              }
            ],
            "url": {
              "raw": "{{baseUrl}}/roles",
              "host": ["{{baseUrl}}"],
              "path": ["roles"]
            },
            "description": "Get all available roles"
          },
          "response": []
        },
        {
          "name": "Get Role by ID",
          "request": {
            "method": "GET",
            "header": [
              {
                "key": "Authorization",
                "value": "Bearer {{token}}"
              }
            ],
            "url": {
              "raw": "{{baseUrl}}/roles/1",
              "host": ["{{baseUrl}}"],
              "path": ["roles", "1"]
            },
            "description": "Get a specific role by ID"
          },
          "response": []
        }
      ]
    }
  ]
}
